{"trial_id": "00", "hyperparameters": {"space": [{"class_name": "Int", "config": {"name": "units", "default": null, "conditions": [], "min_value": 50, "max_value": 200, "step": 50, "sampling": "linear"}}, {"class_name": "Choice", "config": {"name": "optimizer", "default": "adam", "conditions": [], "values": ["adam", "rmsprop"], "ordered": false}}], "values": {"units": 50, "optimizer": "rmsprop"}}, "metrics": {"metrics": {"loss": {"direction": "min", "observations": [{"value": [0.0008683226187713444], "step": 47}]}, "val_loss": {"direction": "min", "observations": [{"value": [0.0012515896232798696], "step": 47}]}}}, "score": 0.0012515896232798696, "best_step": 47, "status": "COMPLETED", "message": null}